[{"value": 112, "key": [0, 0]}, {"value": 123, "key": [0, 1]}, {"value": 114, "key": [0, 2]}, {"value": 114, "key": [0, 3]}, {"value": 133, "key": [0, 4]}, {"value": 135, "key": [0, 5]}, {"value": 176, "key": [0, 6]}, {"value": 71, "key": [1, 0]}, {"value": 62, "key": [1, 1]}, {"value": 59, "key": [1, 2]}, {"value": 55, "key": [1, 3]}, {"value": 83, "key": [1, 4]}, {"value": 110, "key": [1, 5]}, {"value": 112, "key": [1, 6]}, {"value": 41, "key": [2, 0]}, {"value": 24, "key": [2, 1]}, {"value": 24, "key": [2, 2]}, {"value": 46, "key": [2, 3]}, {"value": 28, "key": [2, 4]}, {"value": 66, "key": [2, 5]}, {"value": 61, "key": [2, 6]}, {"value": 18, "key": [3, 0]}, {"value": 19, "key": [3, 1]}, {"value": 12, "key": [3, 2]}, {"value": 22, "key": [3, 3]}, {"value": 16, "key": [3, 4]}, {"value": 31, "key": [3, 5]}, {"value": 48, "key": [3, 6]}, {"value": 10, "key": [4, 0]}, {"value": 12, "key": [4, 1]}, {"value": 11, "key": [4, 2]}, {"value": 24, "key": [4, 3]}, {"value": 22, "key": [4, 4]}, {"value": 33, "key": [4, 5]}, {"value": 34, "key": [4, 6]}, {"value": 12, "key": [5, 0]}, {"value": 19, "key": [5, 1]}, {"value": 22, "key": [5, 2]}, {"value": 21, "key": [5, 3]}, {"value": 19, "key": [5, 4]}, {"value": 39, "key": [5, 5]}, {"value": 20, "key": [5, 6]}, {"value": 24, "key": [6, 0]}, {"value": 37, "key": [6, 1]}, {"value": 36, "key": [6, 2]}, {"value": 40, "key": [6, 3]}, {"value": 30, "key": [6, 4]}, {"value": 33, "key": [6, 5]}, {"value": 27, "key": [6, 6]}, {"value": 70, "key": [7, 0]}, {"value": 64, "key": [7, 1]}, {"value": 81, "key": [7, 2]}, {"value": 76, "key": [7, 3]}, {"value": 80, "key": [7, 4]}, {"value": 64, "key": [7, 5]}, {"value": 39, "key": [7, 6]}, {"value": 156, "key": [8, 0]}, {"value": 153, "key": [8, 1]}, {"value": 176, "key": [8, 2]}, {"value": 182, "key": [8, 3]}, {"value": 168, "key": [8, 4]}, {"value": 113, "key": [8, 5]}, {"value": 64, "key": [8, 6]}, {"value": 251, "key": [9, 0]}, {"value": 215, "key": [9, 1]}, {"value": 226, "key": [9, 2]}, {"value": 235, "key": [9, 3]}, {"value": 225, "key": [9, 4]}, {"value": 132, "key": [9, 5]}, {"value": 92, "key": [9, 6]}, {"value": 244, "key": [10, 0]}, {"value": 254, "key": [10, 1]}, {"value": 241, "key": [10, 2]}, {"value": 251, "key": [10, 3]}, {"value": 228, "key": [10, 4]}, {"value": 207, "key": [10, 5]}, {"value": 141, "key": [10, 6]}, {"value": 212, "key": [11, 0]}, {"value": 207, "key": [11, 1]}, {"value": 216, "key": [11, 2]}, {"value": 240, "key": [11, 3]}, {"value": 260, "key": [11, 4]}, {"value": 218, "key": [11, 5]}, {"value": 192, "key": [11, 6]}, {"value": 222, "key": [12, 0]}, {"value": 224, "key": [12, 1]}, {"value": 239, "key": [12, 2]}, {"value": 230, "key": [12, 3]}, {"value": 269, "key": [12, 4]}, {"value": 247, "key": [12, 5]}, {"value": 188, "key": [12, 6]}, {"value": 285, "key": [13, 0]}, {"value": 271, "key": [13, 1]}, {"value": 244, "key": [13, 2]}, {"value": 286, "key": [13, 3]}, {"value": 231, "key": [13, 4]}, {"value": 267, "key": [13, 5]}, {"value": 281, "key": [13, 6]}, {"value": 319, "key": [14, 0]}, {"value": 290, "key": [14, 1]}, {"value": 267, "key": [14, 2]}, {"value": 316, "key": [14, 3]}, {"value": 284, "key": [14, 4]}, {"value": 297, "key": [14, 5]}, {"value": 237, "key": [14, 6]}, {"value": 272, "key": [15, 0]}, {"value": 308, "key": [15, 1]}, {"value": 308, "key": [15, 2]}, {"value": 282, "key": [15, 3]}, {"value": 259, "key": [15, 4]}, {"value": 388, "key": [15, 5]}, {"value": 317, "key": [15, 6]}, {"value": 271, "key": [16, 0]}, {"value": 294, "key": [16, 1]}, {"value": 278, "key": [16, 2]}, {"value": 271, "key": [16, 3]}, {"value": 278, "key": [16, 4]}, {"value": 340, "key": [16, 5]}, {"value": 327, "key": [16, 6]}, {"value": 272, "key": [17, 0]}, {"value": 305, "key": [17, 1]}, {"value": 303, "key": [17, 2]}, {"value": 292, "key": [17, 3]}, {"value": 323, "key": [17, 4]}, {"value": 321, "key": [17, 5]}, {"value": 302, "key": [17, 6]}, {"value": 284, "key": [18, 0]}, {"value": 374, "key": [18, 1]}, {"value": 351, "key": [18, 2]}, {"value": 337, "key": [18, 3]}, {"value": 342, "key": [18, 4]}, {"value": 329, "key": [18, 5]}, {"value": 348, "key": [18, 6]}, {"value": 335, "key": [19, 0]}, {"value": 316, "key": [19, 1]}, {"value": 365, "key": [19, 2]}, {"value": 388, "key": [19, 3]}, {"value": 317, "key": [19, 4]}, {"value": 300, "key": [19, 5]}, {"value": 313, "key": [19, 6]}, {"value": 275, "key": [20, 0]}, {"value": 369, "key": [20, 1]}, {"value": 336, "key": [20, 2]}, {"value": 325, "key": [20, 3]}, {"value": 282, "key": [20, 4]}, {"value": 266, "key": [20, 5]}, {"value": 259, "key": [20, 6]}, {"value": 244, "key": [21, 0]}, {"value": 279, "key": [21, 1]}, {"value": 268, "key": [21, 2]}, {"value": 301, "key": [21, 3]}, {"value": 295, "key": [21, 4]}, {"value": 260, "key": [21, 5]}, {"value": 232, "key": [21, 6]}, {"value": 214, "key": [22, 0]}, {"value": 208, "key": [22, 1]}, {"value": 214, "key": [22, 2]}, {"value": 248, "key": [22, 3]}, {"value": 270, "key": [22, 4]}, {"value": 255, "key": [22, 5]}, {"value": 208, "key": [22, 6]}, {"value": 161, "key": [23, 0]}, {"value": 172, "key": [23, 1]}, {"value": 223, "key": [23, 2]}, {"value": 171, "key": [23, 3]}, {"value": 208, "key": [23, 4]}, {"value": 207, "key": [23, 5]}, {"value": 170, "key": [23, 6]}]